README.rst
setup.cfg
setup.py
pyRFC3339.egg-info/PKG-INFO
pyRFC3339.egg-info/SOURCES.txt
pyRFC3339.egg-info/dependency_links.txt
pyRFC3339.egg-info/requires.txt
pyRFC3339.egg-info/top_level.txt
pyrfc3339/__init__.py
pyrfc3339/generator.py
pyrfc3339/parser.py
pyrfc3339/utils.py
pyrfc3339/tests/__init__.py
pyrfc3339/tests/tests.py