Metadata-Version: 1.1
Name: pyRFC3339
Version: 0.2
Summary: Generate and parse RFC 3339 timestamps
Home-page: UNKNOWN
Author: Kurt Raschke
Author-email: kurt@kurtraschke.com
License: MIT
Keywords: rfc 3339 timestamp
Platform: UNKNOWN
Classifier: Development Status :: 5 - Production/Stable
Classifier: Intended Audience :: Developers
Classifier: License :: OSI Approved :: MIT License
Classifier: Programming Language :: Python
Classifier: Topic :: Internet
